requests_downloader/__init__.py
requests_downloader/cli.py
requests_downloader/downloader.py
requests_downloader/handlers.py
requests_downloader/utils.py
requests_downloader-0.4.1.dist-info/AUTHORS.rst
requests_downloader-0.4.1.dist-info/LICENSE
requests_downloader-0.4.1.dist-info/METADATA
requests_downloader-0.4.1.dist-info/WHEEL
requests_downloader-0.4.1.dist-info/entry_points.txt
requests_downloader-0.4.1.dist-info/top_level.txt
requests_downloader-0.4.1.dist-info/RECORD
