Metadata-Version: 2.1
Name: requests-downloader
Version: 0.4.1
Summary: Python package to download files
Home-page: https://github.com/hrishikeshrt/requests_downloader
Author: Hrishikesh Terdalkar
Author-email: hrishikeshrt@linuxmail.org
License: GNU General Public License v3
Keywords: requests_downloader
Platform: UNKNOWN
Classifier: Development Status :: 4 - Beta
Classifier: Intended Audience :: Developers
Classifier: License :: OSI Approved :: GNU General Public License v3 (GPLv3)
Classifier: Natural Language :: English
Classifier: Topic :: Internet
Classifier: Topic :: Utilities
Classifier: Programming Language :: Python :: 3
Classifier: Programming Language :: Python :: 3.6
Classifier: Programming Language :: Python :: 3.7
Classifier: Programming Language :: Python :: 3.8
Requires-Python: >=3.6
License-File: LICENSE
License-File: AUTHORS.rst
Requires-Dist: requests
Requires-Dist: tqdm
Requires-Dist: beautifulsoup4
